MANIFEST.in
README.md
README.rst
setup.py
wpa_supplicant/__init__.py
wpa_supplicant/cli.py
wpa_supplicant/core.py
wpa_supplicant.egg-info/PKG-INFO
wpa_supplicant.egg-info/SOURCES.txt
wpa_supplicant.egg-info/dependency_links.txt
wpa_supplicant.egg-info/entry_points.txt
wpa_supplicant.egg-info/requires.txt
wpa_supplicant.egg-info/top_level.txt
wpa_supplicant/test/__init__.py
wpa_supplicant/test/mocks.py
wpa_supplicant/test/test_cli.py
wpa_supplicant/test/test_core.py