Metadata-Version: 1.1
Name: wpa-supplicant
Version: 0.1
Summary: WPA Supplicant wrapper for Python
Home-page: UNKNOWN
Author: Stephen Stack
Author-email: Stephen.Stack@digi.com
License: UNKNOWN
Platform: UNKNOWN
Classifier: Development Status :: 3 - Alpha
Classifier: Intended Audience :: Developers
Classifier: License :: OSI Approved :: Mozilla Public License 2.0 (MPL 2.0)
Classifier: Programming Language :: Python :: 2.7
Classifier: Topic :: Software Development :: Libraries
Classifier: Operating System :: POSIX :: Linux
